sbol_utilities/__init__.py
sbol_utilities/calculate_sequences.py
sbol_utilities/component.py
sbol_utilities/conversion.py
sbol_utilities/excel_to_sbol.py
sbol_utilities/expand_combinatorial_derivations.py
sbol_utilities/gb2so.csv
sbol_utilities/graph_sbol.py
sbol_utilities/helper_functions.py
sbol_utilities/sbol3_genbank_conversion.py
sbol_utilities/sbol_diff.py
sbol_utilities/sbolgraph-standalone.js
sbol_utilities/sequence.py
sbol_utilities/so2gb.csv
sbol_utilities/workarounds.py
sbol_utilities-1.0a17.dist-info/LICENSE.txt
sbol_utilities-1.0a17.dist-info/METADATA
sbol_utilities-1.0a17.dist-info/WHEEL
sbol_utilities-1.0a17.dist-info/entry_points.txt
sbol_utilities-1.0a17.dist-info/top_level.txt
sbol_utilities-1.0a17.dist-info/RECORD
