Metadata-Version: 2.1
Name: sbol-utilities
Version: 1.0a17
Summary: SBOL utilities
Home-page: https://github.com/SynBioDex/SBOL-utilities
License: MIT License
Keywords: synthetic biology
Classifier: Development Status :: 3 - Alpha
Classifier: Intended Audience :: Developers
Classifier: License :: OSI Approved :: MIT License
Classifier: Programming Language :: Python :: 3 :: Only
Classifier: Programming Language :: Python :: 3.7
Classifier: Programming Language :: Python :: 3.8
Classifier: Programming Language :: Python :: 3.9
Classifier: Programming Language :: Python :: 3.10
Classifier: Programming Language :: Python :: 3.11
License-File: LICENSE.txt
Requires-Dist: sbol3 (>=1.1)
Requires-Dist: sbol2 (>=1.4)
Requires-Dist: rdflib (>=6.2)
Requires-Dist: biopython
Requires-Dist: graphviz
Requires-Dist: tyto (>=1.4)
Requires-Dist: openpyxl
Requires-Dist: sbol-factory (>=1.1)
Provides-Extra: dev
Requires-Dist: pytest ; extra == 'dev'
Requires-Dist: interrogate ; extra == 'dev'
